pybraces/__init__.py
pybraces/__main__.py
pybrkarma-1.1.5.dist-info/licenses/LICENSE
pybrkarma-1.1.5.dist-info/METADATA
pybrkarma-1.1.5.dist-info/WHEEL
pybrkarma-1.1.5.dist-info/entry_points.txt
pybrkarma-1.1.5.dist-info/top_level.txt
pybrkarma-1.1.5.dist-info/RECORD
