Metadata-Version: 2.4
Name: PyBrKarma
Version: 1.1.5
Summary: PyBrKarma - Python with Braces Runtime Transformer
Home-page: https://github.com/Salehin-07/PyBrKarma
Author: Md Abu Salehin
Author-email: mdabusalehin123@gmail.com
Classifier: Programming Language :: Python :: 3
Classifier: License :: OSI Approved :: MIT License
Classifier: Operating System :: OS Independent
Requires-Python: >=3.6
License-File: LICENSE
Dynamic: author
Dynamic: author-email
Dynamic: classifier
Dynamic: description
Dynamic: description-content-type
Dynamic: home-page
Dynamic: license-file
Dynamic: requires-python
Dynamic: summary
